{
  "ETTh1": {
    "96": {
      "mse": 0.417128,
      "mae": 0.43456
    },
    "192": {
      "mse": 0.44559,
      "mae": 0.44877
    },
    "336": {
      "mse": 0.46757,
      "mae": 0.462049
    },
    "720": {
      "mse": 0.484893,
      "mae": 0.483009
    }
  },
  "ETTh2": {
    "96": {
      "mse": 0.303598,
      "mae": 0.355962
    },
    "192": {
      "mse": 0.378335,
      "mae": 0.401611
    },
    "336": {
      "mse": 0.397864,
      "mae": 0.423604
    },
    "720": {
      "mse": 0.422554,
      "mae": 0.448561
    }
  },
  "exchange_rate": {
    "96": {
      "mse": 0.118156,
      "mae": 0.25104
    },
    "192": {
      "mse": 0.212315,
      "mae": 0.331767
    },
    "336": {
      "mse": 0.375127,
      "mae": 0.453274
    },
    "720": {
      "mse": 0.9796,
      "mae": 0.753421
    }
  }
}